yourls/__init__.py
yourls/__main__.py
yourls/core.py
yourls/data.py
yourls/exceptions.py
yourls/log.py
yourls-1.2.3.dist-info/DESCRIPTION.rst
yourls-1.2.3.dist-info/METADATA
yourls-1.2.3.dist-info/RECORD
yourls-1.2.3.dist-info/WHEEL
yourls-1.2.3.dist-info/entry_points.txt
yourls-1.2.3.dist-info/metadata.json
yourls-1.2.3.dist-info/top_level.txt
