Metadata-Version: 2.0
Name: yourls
Version: 1.2.3
Summary: Python client for YOURLS.
Home-page: https://github.com/razerm/yourls-python
Author: Frazer McLean
Author-email: frazer@frazermclean.co.uk
License: MIT
Platform: UNKNOWN
Classifier: Development Status :: 5 - Production/Stable
Classifier: License :: OSI Approved :: MIT License
Classifier: Programming Language :: Python :: 2.7
Classifier: Programming Language :: Python :: 3
Requires-Dist: click
Requires-Dist: logbook (>=0.10.0)
Requires-Dist: represent (>=1.4.0)
Requires-Dist: requests
Requires-Dist: six
Provides-Extra: dev
Requires-Dist: coverage; extra == 'dev'
Requires-Dist: doc8; extra == 'dev'
Requires-Dist: flake8; extra == 'dev'
Requires-Dist: flake8-coding; extra == 'dev'
Requires-Dist: flake8-future-import; extra == 'dev'
Requires-Dist: pep8-naming; extra == 'dev'
Requires-Dist: plumbum; extra == 'dev'
Requires-Dist: pyenchant; extra == 'dev'
Requires-Dist: shovel; extra == 'dev'
Requires-Dist: sphinx; extra == 'dev'
Requires-Dist: sphinx-rtd-theme; extra == 'dev'
Requires-Dist: sphinxcontrib-spelling; extra == 'dev'
Requires-Dist: tox; extra == 'dev'
Requires-Dist: watchdog; extra == 'dev'
Requires-Dist: pytest (>=2.7.3); extra == 'dev'
Requires-Dist: responses; extra == 'dev'
Provides-Extra: dev
Requires-Dist: mock; python_version<"3.3" and extra == 'dev'
Provides-Extra: test
Requires-Dist: pytest (>=2.7.3); extra == 'test'
Requires-Dist: responses; extra == 'test'
Provides-Extra: test
Requires-Dist: mock; python_version<"3.3" and extra == 'test'
